{"chunk_definitions":[{"chunk_id":"csetup_chunk","chunk_label":"setup","document_id":"39604BA","expansion_state":0,"options":{"engine":"r","include":false,"label":"setup"},"row":54,"row_count":1,"visible":true},{"chunk_id":"c64gn6n07lit7","chunk_label":"unnamed-chunk-1","document_id":"39604BA","expansion_state":0,"options":{"dev":"svg","echo":false,"engine":"r","fig.cap":"Datos de ponteencarrera.pe y MTPE - OGETIC - OE - Planilla Electrónica 2017","fig.height":14,"fig.width":7,"label":"unnamed-chunk-46"},"row":79,"row_count":1,"visible":true},{"chunk_id":"c8h4kzcu6plf1","chunk_label":"unnamed-chunk-2","document_id":"39604BA","expansion_state":0,"options":{"dev":"svg","echo":false,"engine":"r","fig.cap":"Datos de ponteencarrera.pe y MTPE - OGETIC - OE - Planilla Electrónica 2017","fig.height":9,"fig.width":7,"label":"unnamed-chunk-101"},"row":99,"row_count":1,"visible":true},{"chunk_id":"c7f9d6ditl4qk","chunk_label":"unnamed-chunk-2","document_id":"39604BA","expansion_state":0,"options":{"dev":"svg","echo":false,"engine":"r","fig.cap":"Datos de ponteencarrera.pe y MTPE - OGETIC - OE - Planilla Electrónica 2017","fig.height":14,"fig.width":7,"label":"unnamed-chunk-30"},"row":100,"row_count":1,"visible":true},{"chunk_id":"c5iezfmt619o3","chunk_label":"unnamed-chunk-3","document_id":"39604BA","expansion_state":0,"options":{"dev":"svg","echo":false,"engine":"r","fig.height":6,"fig.width":8,"label":"unnamed-chunk-102"},"row":127,"row_count":1,"visible":true},{"chunk_id":"ceh7mk894hm2f","chunk_label":"unnamed-chunk-4","document_id":"39604BA","expansion_state":0,"options":{"dev":"svg","echo":false,"engine":"r","fig.height":6,"fig.width":8,"label":"unnamed-chunk-104"},"row":156,"row_count":1,"visible":true}],"default_chunk_options":{"echo":true},"doc_write_time":1577065082,"working_dir":null}